supex/__init__.py
supex/models/__init__.py
supex/models/reco/__init__.py
supex/models/reco/sequential/__init__.py
supex/models/reco/sequential/big_recbole_model.py
supex/utils/__init__.py
supex/utils/skt_hash.py
supex-2023.4.12.dist-info/LICENSE
supex-2023.4.12.dist-info/METADATA
supex-2023.4.12.dist-info/WHEEL
supex-2023.4.12.dist-info/top_level.txt
supex-2023.4.12.dist-info/RECORD
