Metadata-Version: 2.1
Name: supex
Version: 2023.4.12
Summary: skt_ca_team library
Home-page: https://github.com/sktaiflow/advanced_analytics
Author: skt_ca_team
Author-email: rbska56455@gmail.com
License: UNKNOWN
Platform: UNKNOWN
Classifier: Programming Language :: Python :: 3
Classifier: License :: OSI Approved :: MIT License
Classifier: Operating System :: OS Independent
Requires-Python: >=3.6
License-File: LICENSE
Requires-Dist: autogluon.tabular
Requires-Dist: recbole
